{
  "$schema": "http://json-schema.org/draft-07/schema#",
  "title": "notification-triggersInput",
  "description": "Input schema for Configurable regex-based alert system for detecting patterns in tool calls and session activity. Supports error triggers, content regex matching, token threshold triggers, and pattern detection with configurable actions.",
  "type": "object",
  "additionalProperties": true,
  "properties": {
    "target": {
      "type": "string",
      "description": "Target file or path for the skill to operate on"
    },
    "options": {
      "type": "object",
      "description": "Additional options for skill execution",
      "additionalProperties": true
    }
  }
}
